tgdb/__init__.py
tgdb/py.typed
tgdb/application/__init__.py
tgdb/application/common/__init__.py
tgdb/application/common/operator.py
tgdb/application/common/ports/__init__.py
tgdb/application/common/ports/buffer.py
tgdb/application/common/ports/clock.py
tgdb/application/common/ports/queque.py
tgdb/application/common/ports/uuids.py
tgdb/application/horizon/__init__.py
tgdb/application/horizon/commit_transaction.py
tgdb/application/horizon/output_commits.py
tgdb/application/horizon/output_commits_to_tuples.py
tgdb/application/horizon/rollback_transaction.py
tgdb/application/horizon/start_transaction.py
tgdb/application/horizon/ports/__init__.py
tgdb/application/horizon/ports/channel.py
tgdb/application/horizon/ports/shared_horizon.py
tgdb/application/relation/__init__.py
tgdb/application/relation/create_relation.py
tgdb/application/relation/view_all_relations.py
tgdb/application/relation/view_relation.py
tgdb/application/relation/view_tuples.py
tgdb/application/relation/ports/__init__.py
tgdb/application/relation/ports/relation_views.py
tgdb/application/relation/ports/relations.py
tgdb/application/relation/ports/tuples.py
tgdb/entities/__init__.py
tgdb/entities/horizon/__init__.py
tgdb/entities/horizon/claim.py
tgdb/entities/horizon/horizon.py
tgdb/entities/horizon/transaction.py
tgdb/entities/numeration/__init__.py
tgdb/entities/numeration/number.py
tgdb/entities/relation/__init__.py
tgdb/entities/relation/domain.py
tgdb/entities/relation/relation.py
tgdb/entities/relation/scalar.py
tgdb/entities/relation/schema.py
tgdb/entities/relation/tuple.py
tgdb/entities/relation/tuple_effect.py
tgdb/entities/relation/versioned_tuple.py
tgdb/entities/time/__init__.py
tgdb/entities/time/logic_time.py
tgdb/entities/tools/__init__.py
tgdb/entities/tools/assert_.py
tgdb/entities/tools/map.py
tgdb/infrastructure/__init__.py
tgdb/infrastructure/async_map.py
tgdb/infrastructure/async_queque.py
tgdb/infrastructure/heap_tuple_encoding.py
tgdb/infrastructure/lazy_map.py
tgdb-0.1.0.dist-info/METADATA
tgdb-0.1.0.dist-info/WHEEL
tgdb-0.1.0.dist-info/entry_points.txt
tgdb-0.1.0.dist-info/licenses/LICENSE
tgdb-0.1.0.dist-info/RECORD
