Metadata-Version: 2.4
Name: tgdb
Version: 0.1.0
Summary: RDBMS over Telegram
Project-URL: Repository, https://github.com/emptybutton/tgdb
Author-email: Alexander Smolin <88573504+emptybutton@users.noreply.github.com>
License:                                  Apache License
License-File: LICENSE
Requires-Python: >=3.13
Requires-Dist: dishka>=1.4.2
Requires-Dist: fastapi>=0.115.2
Requires-Dist: in-memory-db>=0.3.0
Requires-Dist: pydantic>=2.11.4
Requires-Dist: pyyaml>=6.0.2
Requires-Dist: telethon>=1.40.0
Requires-Dist: typenv>=0.2.0
Requires-Dist: uvicorn[standard]>=0.30.6
Provides-Extra: dev
Requires-Dist: dirty-equals==0.9.0; extra == 'dev'
Requires-Dist: httpx-ws==0.7.2; extra == 'dev'
Requires-Dist: httpx==0.28.1; extra == 'dev'
Requires-Dist: mypy[faster-cache]==1.16.0; extra == 'dev'
Requires-Dist: pytest-asyncio==1.0.0; extra == 'dev'
Requires-Dist: pytest-cov==6.1.1; extra == 'dev'
Requires-Dist: pytest-timeout==2.4.0; extra == 'dev'
Requires-Dist: pytest==8.4.0; extra == 'dev'
Requires-Dist: ruff==0.11.13; extra == 'dev'
Requires-Dist: types-pyyaml==6.0.12.20250516; extra == 'dev'
